LICENSE.txt
MANIFEST.in
README.md
setup.py
jk_pathpatternmatcher2/Entry.py
jk_pathpatternmatcher2/IFabricIOAdapter.py
jk_pathpatternmatcher2/ILocalDiskIOAdapter.py
jk_pathpatternmatcher2/IParamicoIOAdapter.py
jk_pathpatternmatcher2/IWalkIOAdapter.py
jk_pathpatternmatcher2/PathPatternMatcher.py
jk_pathpatternmatcher2/PathPatternMatcherCollection.py
jk_pathpatternmatcher2/__init__.py
jk_pathpatternmatcher2/pm.py
jk_pathpatternmatcher2/walk.py
jk_pathpatternmatcher2.egg-info/PKG-INFO
jk_pathpatternmatcher2.egg-info/SOURCES.txt
jk_pathpatternmatcher2.egg-info/dependency_links.txt
jk_pathpatternmatcher2.egg-info/not-zip-safe
jk_pathpatternmatcher2.egg-info/requires.txt
jk_pathpatternmatcher2.egg-info/top_level.txt