Metadata-Version: 2.1
Name: jk-pathpatternmatcher2
Version: 0.2021.9.10
Summary: A python module to perform pattern matching tasks on paths.
Home-page: UNKNOWN
Author: Jürgen Knauth
Author-email: pubsrc@binary-overflow.de
License: Apache2
Keywords: filesystem,pattern-matching
Platform: UNKNOWN
Classifier: Development Status :: 5 - Production/Stable
Classifier: License :: OSI Approved :: Apache Software License
Classifier: Programming Language :: Python :: 3
